meez/__init__.py
meez/core/__init__.py
meez/core/general_respond.py
meez/core/intention.py
meez/core/langchain.py
meez/core/langgraph.py
meez/core/respond.py
meez/data/__init__.py
meez/data/reader.py
meez/exception/__init__.py
meez/exception/api_error.py
meez/util/__init__.py
meez/util/file_system.py
meez/util/logger.py
meez-0.3.4.dist-info/licenses/LICENSE.txt
meez-0.3.4.dist-info/METADATA
meez-0.3.4.dist-info/WHEEL
meez-0.3.4.dist-info/top_level.txt
meez-0.3.4.dist-info/RECORD
