Metadata-Version: 2.4
Name: Meez
Version: 0.3.4
Summary: AI Assistant and Copilot SDK for SaaS Applications
Home-page: https://github.com/clivern/meez/
Author: clivern
Author-email: hello@clivern.com
License: Apache Software License
Project-URL: Documentation, https://github.com/clivern/meez/
Project-URL: Source, https://github.com/clivern/meez/
Project-URL: Changelog, https://github.com/clivern/meez/blob/main/CHANGELOG.rst
Project-URL: Tracker, https://github.com/clivern/meez/issues
Project-URL: Download, https://pypi.org/project/meez/#files
Platform: any
Classifier: Development Status :: 5 - Production/Stable
Classifier: Programming Language :: Python
Classifier: License :: OSI Approved :: Apache Software License
License-File: LICENSE.txt
Requires-Dist: langchain<=0.3.27
Requires-Dist: langchain-openai<=0.3.33
Requires-Dist: openai<=1.105.0
Requires-Dist: langgraph<=0.6.7
Requires-Dist: requests<=2.32.5
Requires-Dist: importlib-metadata; python_version < "3.8"
Dynamic: license-file
